profe/.DS_Store
profe/calibrate/.DS_Store
profe/output/__init__.py
profe/output/alt_az_centroid.py
profe/output/cli.py
profe/output/correlated_noise.py
profe/output/exofop_out.py
profe/output/light_curves.py
profe/preprocess/__init__.py
profe/preprocess/cli.py
profe/preprocess/fits_processor.py
profe/preprocess/median_filter.py
profe-0.1.1.dist-info/LICENSE
profe-0.1.1.dist-info/METADATA
profe-0.1.1.dist-info/WHEEL
profe-0.1.1.dist-info/entry_points.txt
profe-0.1.1.dist-info/RECORD
