Metadata-Version: 2.3
Name: profe
Version: 0.1.1
Summary: Reduction Pipeline for OPTICAM Photometry of Exoplanets (PROFE in spanish)
License: MIT
Author: S. Paez
Author-email: spaez@astro.unam.mx
Requires-Python: >=3.11,<3.12
Classifier: License :: OSI Approved :: MIT License
Classifier: Programming Language :: Python :: 3
Classifier: Programming Language :: Python :: 3.11
Requires-Dist: astropy (==5.3.2)
Requires-Dist: black (>=25.1.0,<26.0.0)
Requires-Dist: matplotlib (>=3.10.3,<4.0.0)
Requires-Dist: mc3 (>=3.2.1,<4.0.0)
Requires-Dist: numpy (>=1.24,<2.0)
Requires-Dist: pandas (>=2.3.1,<3.0.0)
Requires-Dist: pandas-stubs (>=2.3.0.250703,<3.0.0.0)
Requires-Dist: photutils (>=2.2.0,<3.0.0)
Requires-Dist: scipy (>=1.10,<2.0)
Requires-Dist: tqdm (>=4.67.1,<5.0.0)
Requires-Dist: types-tqdm (>=4.67.0.20250516,<5.0.0.0)
